alchmanager/__init__.py
alchmanager/alchmanager.py
advanced_sqlalchemy_manager-0.1.1.dist-info/LICENSE.txt
advanced_sqlalchemy_manager-0.1.1.dist-info/METADATA
advanced_sqlalchemy_manager-0.1.1.dist-info/WHEEL
advanced_sqlalchemy_manager-0.1.1.dist-info/top_level.txt
advanced_sqlalchemy_manager-0.1.1.dist-info/RECORD
