Metadata-Version: 2.1
Name: advanced-sqlalchemy-manager
Version: 0.1.1
Summary: Advanced query manager for SQLAlchemy
Home-page: https://github.com/Flowelcat/advanced-sqlalchemy-manager
Author: Flowelcat
Author-email: flowelcat@gmail.com
License: GNUv3
Keywords: sqlalchemy,alchmanager,query_manager,query
Platform: UNKNOWN
Classifier: License :: OSI Approved :: GNU General Public License v3 (GPLv3)
Classifier: Intended Audience :: Developers
Classifier: Programming Language :: Python
Classifier: Programming Language :: Python :: 3
Classifier: Programming Language :: Python :: 3.5
Classifier: Programming Language :: Python :: 3.6
Classifier: Programming Language :: Python :: 3.7
Classifier: Programming Language :: Python :: 3.8
Classifier: Programming Language :: Python :: 3.9
Requires-Python: >=3.5
License-File: LICENSE.txt
Requires-Dist: sqlalchemy
